PHX/__init__.py
PHX/_hbjson_to_phpp.sh
PHX/hbjson_to_phpp.py
PHX/hbjson_to_wufi_xml.py
PHX/run.py
PHX/PHPP/README.md
PHX/PHPP/__init__.py
PHX/PHPP/phpp_app.py
PHX/PHPP/phpp_localization/EN_10_3.json
PHX/PHPP/phpp_localization/EN_10_4A.json
PHX/PHPP/phpp_localization/EN_10_4IP.json
PHX/PHPP/phpp_localization/EN_10_6.json
PHX/PHPP/phpp_localization/EN_10_6IP.json
PHX/PHPP/phpp_localization/EN_9_6A.json
PHX/PHPP/phpp_localization/EN_9_7IP.json
PHX/PHPP/phpp_localization/__init__.py
PHX/PHPP/phpp_localization/load.py
PHX/PHPP/phpp_localization/shape_model.py
PHX/PHPP/phpp_model/__init__.py
PHX/PHPP/phpp_model/areas_data.py
PHX/PHPP/phpp_model/areas_surface.py
PHX/PHPP/phpp_model/areas_thermal_bridges.py
PHX/PHPP/phpp_model/climate_entry.py
PHX/PHPP/phpp_model/component_frame.py
PHX/PHPP/phpp_model/component_glazing.py
PHX/PHPP/phpp_model/component_vent.py
PHX/PHPP/phpp_model/elec_non_res.py
PHX/PHPP/phpp_model/electricity_item.py
PHX/PHPP/phpp_model/hot_water_piping.py
PHX/PHPP/phpp_model/hot_water_tank.py
PHX/PHPP/phpp_model/shading_rows.py
PHX/PHPP/phpp_model/uvalues_constructor.py
PHX/PHPP/phpp_model/vent_ducts.py
PHX/PHPP/phpp_model/vent_space.py
PHX/PHPP/phpp_model/vent_units.py
PHX/PHPP/phpp_model/ventilation_data.py
PHX/PHPP/phpp_model/verification_data.py
PHX/PHPP/phpp_model/version.py
PHX/PHPP/phpp_model/windows_rows.py
PHX/PHPP/sheet_io/__init__.py
PHX/PHPP/sheet_io/io_PER.py
PHX/PHPP/sheet_io/io_addnl_vent.py
PHX/PHPP/sheet_io/io_areas.py
PHX/PHPP/sheet_io/io_climate.py
PHX/PHPP/sheet_io/io_components.py
PHX/PHPP/sheet_io/io_cooling_demand.py
PHX/PHPP/sheet_io/io_cooling_peak_load.py
PHX/PHPP/sheet_io/io_cooling_units.py
PHX/PHPP/sheet_io/io_elec_non_res.py
PHX/PHPP/sheet_io/io_electricity.py
PHX/PHPP/sheet_io/io_exceptions.py
PHX/PHPP/sheet_io/io_heating_demand.py
PHX/PHPP/sheet_io/io_heating_peak_load.py
PHX/PHPP/sheet_io/io_hot_water.py
PHX/PHPP/sheet_io/io_ihg_non_res.py
PHX/PHPP/sheet_io/io_overview.py
PHX/PHPP/sheet_io/io_shading.py
phx-1.53.1.dist-info/licenses/LICENSE
phx-1.53.1.dist-info/METADATA
phx-1.53.1.dist-info/WHEEL
phx-1.53.1.dist-info/top_level.txt
phx-1.53.1.dist-info/RECORD
