Metadata-Version: 2.4
Name: phx
Version: 1.53.1
Summary: Input / Output Passive House building energy model data.
Home-page: https://github.com/PH-Tools/PHX
Author: PH-Tools
Author-email: phtools@bldgtyp.com
License: GPLv3+
Classifier: Programming Language :: Python :: 2
Classifier: Programming Language :: Python :: 2.7
Classifier: Programming Language :: Python :: 3
Classifier: Programming Language :: Python :: 3.10
Classifier: Programming Language :: Python :: Implementation :: CPython
Classifier: License :: OSI Approved :: GNU General Public License v3 or later (GPLv3+)
Classifier: Operating System :: OS Independent
Classifier: Typing :: Typed
License-File: LICENSE
Requires-Dist: honeybee-core>=1.64.9
Requires-Dist: honeybee-energy>=1.116.103
Requires-Dist: honeybee-ph>=1.32.0
Requires-Dist: pydantic<2.0
Requires-Dist: PH-units>=1.5.26
Requires-Dist: rich
Requires-Dist: xlwings
Requires-Dist: lxml
Dynamic: description
Dynamic: description-content-type
Dynamic: license-file
Dynamic: requires-dist
